config_handler/__init__.py
config_handler/__main__.py
config_handler/advanced.py
config_handler/ciphers.py
config_handler/exceptions.py
config_handler/info.py
config_handler/simple.py
py_config_handler-1.0.2.dist-info/LICENSE.md
py_config_handler-1.0.2.dist-info/METADATA
py_config_handler-1.0.2.dist-info/WHEEL
py_config_handler-1.0.2.dist-info/entry_points.txt
py_config_handler-1.0.2.dist-info/top_level.txt
py_config_handler-1.0.2.dist-info/RECORD
