Metadata-Version: 2.1
Name: py-config-handler
Version: 1.0.2
Summary: Create, update, and remove values from a configuration file made by ConfigHandler.
Home-page: https://github.com/Chris1320/ConfigHandler-python
Author: Chris1320
Author-email: chris1320is@protonmail.com
License: MIT
Platform: UNKNOWN
Classifier: Development Status :: 4 - Beta
Classifier: License :: OSI Approved :: MIT License
Classifier: Programming Language :: Python :: 3.7
License-File: LICENSE.md
Provides-Extra: aes_encryption
Requires-Dist: pycryptodomex ; extra == 'aes_encryption'
Provides-Extra: lz4_compression
Requires-Dist: lz4 ; extra == 'lz4_compression'
Provides-Extra: pretty_table
Requires-Dist: prettytable ; extra == 'pretty_table'
